{
  "before": {
    "id": 505,
    "name": "MIKROVALE",
    "description": null,
    "image": null,
    "parentId": 496,
    "specs": null,
    "createdAt": "2025-11-12T10:31:59.784Z",
    "updatedAt": "2025-11-12T10:31:59.784Z"
  },
  "specsFromCsv": [
    "Ekran",
    "Funksion shkrirje",
    "Funksioni",
    "Fuqia",
    "Fuqia e grilles",
    "Grill",
    "Hapja e deres",
    "Kapaciteti",
    "Koha Max e gatimit",
    "Komandimi",
    "Ngjyra",
    "Nivele Ngrohje",
    "Permasat LxGJxTH(cm)",
    "Programe automatike",
    "Sinjal akustik",
    "Sistem Eco"
  ]
}